belch/__init__.py
belch/belch.py
belch-1.1.2.dist-info/LICENSE
belch-1.1.2.dist-info/METADATA
belch-1.1.2.dist-info/WHEEL
belch-1.1.2.dist-info/entry_points.txt
belch-1.1.2.dist-info/top_level.txt
belch-1.1.2.dist-info/RECORD
