Metadata-Version: 2.1
Name: belch
Version: 1.1.2
Summary: Password list generator
Home-page: https://github.com/croketillo/belch
Author: croketillo
Author-email: croketillo@gmail.com
License: GNU GENERAL PUBLIC LICENSE
Keywords: Password,Password generator
Classifier: Environment :: Console
Classifier: Intended Audience :: End Users/Desktop
Classifier: Intended Audience :: Other Audience
Classifier: Intended Audience :: Telecommunications Industry
Classifier: Intended Audience :: System Administrators
Classifier: Programming Language :: Python :: 3
Classifier: Programming Language :: Python :: 3.6
Classifier: Programming Language :: Python :: 3.7
Classifier: Programming Language :: Python :: 3.8
Classifier: Topic :: Terminals
Classifier: Topic :: Security
Classifier: Topic :: Utilities
License-File: LICENSE
Requires-Dist: colorama
Requires-Dist: tinyprogress
